sns_pipe-0.1.data/scripts/sns-pipe
snspipe/__init__.py
sns_pipe-0.1.dist-info/metadata.json
sns_pipe-0.1.dist-info/METADATA
sns_pipe-0.1.dist-info/WHEEL
sns_pipe-0.1.dist-info/top_level.txt
sns_pipe-0.1.dist-info/DESCRIPTION.rst
sns_pipe-0.1.dist-info/RECORD
