Metadata-Version: 2.0
Name: sns-pipe
Version: 0.1
Summary: Publishes standard input to an Amazon SNS topic.
Home-page: https://github.com/BashtonLtd/sns-pipe
Author: Raymond Butcher
Author-email: ray@bashton.com
License: Apache License 2.0
Platform: UNKNOWN
Requires-Dist: boto3
